{
  "id": "01KXR2EKKDGRSZWNXQJA2RT1G8",
  "module_id": "01KXR2C3RACFENBCQ800YKK351",
  "ref_code": "PAT-CORE-API-COMMANDS",
  "title": "Command Pattern — NxGN Actions",
  "slug": "api-commands",
  "purpose": [
    "**AI Summary**: Commands are write operations that modify the database. Production command constructors use IDbContextFactory<ActionsDbContext> and every DbContext-backed command execution method accepts optional ActionsDbContext? dbContext after CancellationToken so commands can run independently or participate in a caller-owned transaction. Save commands use the upsert pattern, delete and lifecycle commands return CommandResult variants, expected domain failures return structured CommandError, and transactional audit rows receive the shared context."
  ],
  "category": "cqrs",
  "zone": "api",
  "status": "current",
  "created_at": "2026-07-17T12:57:32.0030626+00:00",
  "examples": [
    {
      "id": "01KXR2GGVNT7C8KP8P673MT5CR",
      "section_id": "01KXR2GEVEAA5878T050X9HFBE",
      "name": "Command Types Example 1",
      "code": "┌───────────────────┐  ┌───────────────────┐  ┌───────────────────┐\n│  Save{Entity}     │  │  Delete{Entity}   │  │  {Action}{Entity} │\n│  Command          │  │  Command          │  │  Command          │\n├───────────────────┤  ├───────────────────┤  ├───────────────────┤\n│ Upsert (Empty?)   │  │ Bulk by Guid[]    │  │ State transition  │\n│ EntityMapper (DI) │  │ ExecuteDeleteAsync│  │ Cascade effects   │\n│ CommandResult<    │  │ Explicit tx       │  │ Side effects      │\n│ EntityMapperResult│  │ Returns           │  │ Returns           │\n│ <T>>              │  │  CommandResult    │  │  CommandResult<T> │\n└───────────────────┘  └───────────────────┘  └───────────────────┘",
      "is_counter": 0,
      "sort_order": 0,
      "created_at": "2026-07-17T12:58:34.7419102+00:00"
    },
    {
      "id": "01KXR2GH00NGXXM01T53KNANAT",
      "section_id": "01KXR2GF0MBXVK7DEMPBA1EJ5A",
      "name": "Shared Result Types Example 1",
      "code": "/// <summary>\n/// Structured error payload — maps directly to SendProblemAsync parameters.\n/// </summary>\npublic readonly record struct CommandError(string Code, string Message, int StatusCode = 400);\n\n/// <summary>\n/// Result for commands that don't return data (delete, simple lifecycle).\n/// </summary>\npublic record CommandResult\n{\n    public CommandError? Error { get; init; }\n    public bool Succeeded => Error is null;\n\n    public static readonly CommandResult Success = new();\n    public static CommandResult Fail(string code, string message, int statusCode = 400)\n        => new() { Error = new(code, message, statusCode) };\n}\n\n/// <summary>\n/// Result for commands that return data (lifecycle with response DTO, action commands).\n/// </summary>\npublic record CommandResult<T> : CommandResult\n{\n    public T? Value { get; init; }\n\n    public static CommandResult<T> Ok(T value) => new() { Value = value };\n    // Inherits Fail() from base — returns CommandResult<T> via covariance\n    public new static CommandResult<T> Fail(string code, string message, int statusCode = 400)\n        => new() { Error = new(code, message, statusCode) };\n}",
      "language": "csharp",
      "is_counter": 0,
      "sort_order": 1,
      "created_at": "2026-07-17T12:58:34.8814641+00:00"
    },
    {
      "id": "01KXR2GH4RRBNWFYFPXEE6ST96",
      "section_id": "01KXR2GF0MBXVK7DEMPBA1EJ5A",
      "name": "Shared Result Types Example 2",
      "code": "// Error codes:\n// ACTION-001: Action not found (404)\n// ACTION-002: Slug already exists (409)\n// ACTION-003: Cannot modify protected action (422)\n// ACTION-004: Action has active workflows — cannot deactivate (422)",
      "language": "csharp",
      "is_counter": 0,
      "sort_order": 2,
      "created_at": "2026-07-17T12:58:35.0331911+00:00"
    },
    {
      "id": "01KXR2GHA5P9HPY37NR7ETDT5D",
      "section_id": "01KXR2GF58M33JPYBE87DZ9A13",
      "name": "- Post-save side effects (Redis invalidation, audit logging)",
      "code": "1. var mapResult = entityMapper.MapAsync(dtoList, userId, requestLanguageId, defaultLanguageId, ct, db)\n2. if empty result (no NewItems, no UpdatedItems) → return Fail(404)\n3. if (isNew) → db.AddRange(mapResult.NewItems)\n4. Business logic (uniqueness check → Fail(409), guards → Fail(422), cross-entity ops)\n5. try { SaveChangesAsync } catch { TOCTOU → Fail(409) }\n6. Post-save side effects (audit, cache invalidation)\n7. return Ok(mapResult)",
      "is_counter": 0,
      "sort_order": 3,
      "created_at": "2026-07-17T12:58:35.2062792+00:00"
    },
    {
      "id": "01KXR2GHEJ5R4Y3HEDGVHA4649",
      "section_id": "01KXR2GFAAF7H9D38RYFZKZ3Z5",
      "name": "Save Command (Primary Pattern) Example 1",
      "code": "public class SaveActionCommand(\n    IDbContextFactory<ActionsDbContext> dbContextFactory,\n    ActionEntityMapper entityMapper,\n    ILogger<SaveActionCommand> logger)\n{\n    public async Task<CommandResult<EntityMapperResult<ActionEntity>>> ExecuteAsync(\n        SaveActionRequest request, Guid userId,\n        Guid requestLanguageId, Guid defaultLanguageId,\n        CancellationToken ct = default, ActionsDbContext? db = null)\n    {\n        var shouldDisposeContext = db is null;\n        db ??= await dbContextFactory.CreateDbContextAsync(ct);\n        try\n        {\n            // 1. EntityMapper handles create/update detection\n            // 2. Check for empty result (entity not found on update)\n            // 3. AddRange for new entities\n            // 4. Business logic (uniqueness → Fail, guards → Fail)\n            // 5. try { SaveChangesAsync } catch { TOCTOU → Fail }\n            // 6. Post-save best-effort side effects\n            // 7. return Ok(mapResult)\n        }\n        finally\n        {\n            if (shouldDisposeContext)\n                await db.DisposeAsync();\n        }\n    }\n}",
      "language": "csharp",
      "is_counter": 0,
      "sort_order": 4,
      "created_at": "2026-07-17T12:58:35.3472343+00:00"
    },
    {
      "id": "01KXR2GHJQB8J5XC880QN7DCXA",
      "section_id": "01KXR2GFAAF7H9D38RYFZKZ3Z5",
      "name": "Save Command (Primary Pattern) Example 2",
      "code": "var mapResult = await entityMapper.MapAsync(\n    [request], userId, requestLanguageId, defaultLanguageId, ct, db);",
      "language": "csharp",
      "is_counter": 0,
      "sort_order": 5,
      "created_at": "2026-07-17T12:58:35.4815042+00:00"
    },
    {
      "id": "01KXR2GHR7KWQYZPG0RR5RWXAA",
      "section_id": "01KXR2GFAAF7H9D38RYFZKZ3Z5",
      "name": "Save Command (Primary Pattern) Example 3",
      "code": "if (mapResult.NewItems.Count == 0 && mapResult.UpdatedItems.Count == 0)\n    return CommandResult<EntityMapperResult<ActionEntity>>.Fail(\n        \"ACTION-001\", $\"Action with ID '{request.Id}' not found.\", 404);",
      "language": "csharp",
      "is_counter": 0,
      "sort_order": 6,
      "created_at": "2026-07-17T12:58:35.6561581+00:00"
    },
    {
      "id": "01KXR2GHX7K939Y6077Z1N6T2M",
      "section_id": "01KXR2GFAAF7H9D38RYFZKZ3Z5",
      "name": "The command applies the mapper's result to the DbContext",
      "code": "if (mapResult.NewItems.Count > 0)\n    await db.Actions.AddRangeAsync(mapResult.NewItems, ct);\n\nif (mapResult.UpdatedItems.Count > 0)\n    db.Actions.UpdateRange(mapResult.UpdatedItems);\n\nif (mapResult.DeletedItems.Count > 0)\n    db.RemoveRange(mapResult.DeletedItems);",
      "language": "csharp",
      "is_counter": 0,
      "sort_order": 7,
      "created_at": "2026-07-17T12:58:35.8164026+00:00"
    },
    {
      "id": "01KXR2GJ3A4VNHN3VBEVJNS7NW",
      "section_id": "01KXR2GFAAF7H9D38RYFZKZ3Z5",
      "name": "Save Command (Primary Pattern) Example 5",
      "code": "if (mapResult.NewItems.Count > 0)\n{\n    var slug = mapResult.NewItems[0].Slug;\n    var slugExists = await db.Actions\n        .AnyAsync(a => a.Slug == slug, ct);\n\n    if (slugExists)\n        return CommandResult<EntityMapperResult<ActionEntity>>.Fail(\n            \"ACTION-002\", $\"An action with slug '{slug}' already exists.\", 409);\n}",
      "language": "csharp",
      "is_counter": 0,
      "sort_order": 8,
      "created_at": "2026-07-17T12:58:36.0116808+00:00"
    },
    {
      "id": "01KXR2GJ8PCYBBBAFRGPT3SD30",
      "section_id": "01KXR2GFAAF7H9D38RYFZKZ3Z5",
      "name": "Save Command (Primary Pattern) Example 6",
      "code": "try\n{\n    await db.SaveChangesAsync(ct);\n}\ncatch (DbUpdateException ex) when (\n    ex.InnerException?.Message.Contains(\"ix_actions_slug\", StringComparison.OrdinalIgnoreCase) == true\n    || ex.InnerException?.Message.Contains(\"unique\", StringComparison.OrdinalIgnoreCase) == true\n       && ex.InnerException.Message.Contains(\"slug\", StringComparison.OrdinalIgnoreCase) == true)\n{\n    return CommandResult<EntityMapperResult<ActionEntity>>.Fail(\n        \"ACTION-002\", $\"An action with slug '{request.Slug}' already exists.\", 409);\n}",
      "language": "csharp",
      "is_counter": 0,
      "sort_order": 9,
      "created_at": "2026-07-17T12:58:36.1831885+00:00"
    },
    {
      "id": "01KXR2GJDN79R0SNBGGAA30F1E",
      "section_id": "01KXR2GFAAF7H9D38RYFZKZ3Z5",
      "name": "Save Command (Primary Pattern) Example 7",
      "code": "// Redis cache invalidation\ntry\n{\n    await redisDb.KeyDeleteAsync(RedisKeySchema.Action(actionId.ToString()));\n}\ncatch (Exception ex)\n{\n    logger.LogWarning(ex, \"Failed to invalidate cache for action {ActionId}\", actionId);\n}",
      "language": "csharp",
      "is_counter": 0,
      "sort_order": 10,
      "created_at": "2026-07-17T12:58:36.3419406+00:00"
    },
    {
      "id": "01KXR2GJJAMBNVZKWN7MBG4M9M",
      "section_id": "01KXR2GFAAF7H9D38RYFZKZ3Z5",
      "name": "Step 7 — Return success with EntityMapperResult",
      "code": "return CommandResult<EntityMapperResult<ActionEntity>>.Ok(mapResult);",
      "language": "csharp",
      "is_counter": 0,
      "sort_order": 11,
      "created_at": "2026-07-17T12:58:36.4911080+00:00"
    },
    {
      "id": "01KXR2GJQ422K4E44C0J7B0R1C",
      "section_id": "01KXR2GFAAF7H9D38RYFZKZ3Z5",
      "name": "Save Command (Primary Pattern) Example 9",
      "code": "protected override async Task HandleValidatedRequestAsync(\n    SaveActionRequest req, CancellationToken ct)\n{\n    var result = await saveCommand.ExecuteAsync(\n        req, UserId, RequestLanguageId, DefaultLanguageId, ct);\n    if (!result.Succeeded)\n    {\n        await SendProblemAsync(result.Error!.Code, result.Error.StatusCode, result.Error.Message, ct);\n        return;\n    }\n\n    var mapResult = result.Value!;\n    var isNew = mapResult.NewItems.Count > 0;\n    var entity = isNew ? mapResult.NewItems[0] : mapResult.UpdatedItems[0];\n\n    var eventName = isNew ? \"action.created\" : \"action.updated\";\n    await auditService.LogAsync(eventName, \"Action\", entity.Id,\n        new { req.Name, req.Slug }, ct);\n\n    if (isNew)\n        await Send.CreatedAtAsync<GetActionEndpoint>(\n            new { id = entity.Id },\n            new SaveActionResponse(entity.Id), cancellation: ct);\n    else\n        await Send.OkAsync(new SaveActionResponse(entity.Id), ct);\n}",
      "language": "csharp",
      "is_counter": 0,
      "sort_order": 12,
      "created_at": "2026-07-17T12:58:36.6450859+00:00"
    },
    {
      "id": "01KXR2GJWD4FRD7RNGP2NNZRHC",
      "section_id": "01KXR2GFF86JTE76MXTVJJ65K2",
      "name": "Delete Command Example 1",
      "code": "public class DeleteWorkflowCommand(IDbContextFactory<ActionsDbContext> dbContextFactory)\n{\n    public async Task<CommandResult> ExecuteAsync(\n        Guid[] keys, CancellationToken ct = default, ActionsDbContext? db = null)\n    {\n        var shouldDisposeContext = db is null;\n        db ??= await dbContextFactory.CreateDbContextAsync(ct);\n        try\n        {\n            // Protection check — returns structured error\n            var protectedWorkflows = await db.Workflows\n                .AsNoTracking()\n                .Where(w => keys.Contains(w.Id) && w.IsSystemProtected)\n                .Select(w => w.Name)\n                .ToListAsync(ct);\n\n            if (protectedWorkflows.Count > 0)\n                return CommandResult.Fail(\"WORKFLOW-001\",\n                    $\"Cannot delete protected workflows: {string.Join(\", \", protectedWorkflows)}\", 422);\n\n            // Explicit transaction — prevents partial deletes on failure\n            await using var tx = await db.Database.BeginTransactionAsync(ct);\n\n            await db.WorkflowSteps\n                .Where(s => keys.Contains(s.WorkflowId))\n                .ExecuteDeleteAsync(ct);\n\n            await db.WorkflowTriggers\n                .Where(t => keys.Contains(t.WorkflowId))\n                .ExecuteDeleteAsync(ct);\n\n            await db.Workflows\n                .Where(w => keys.Contains(w.Id))\n                .ExecuteDeleteAsync(ct);\n\n            await tx.CommitAsync(ct);\n            return CommandResult.Success;\n        }\n        finally\n        {\n            if (shouldDisposeContext)\n                await db.DisposeAsync();\n        }\n    }\n}",
      "language": "csharp",
      "is_counter": 0,
      "sort_order": 13,
      "created_at": "2026-07-17T12:58:36.8142801+00:00"
    },
    {
      "id": "01KXR2GK1FTVT1KCXF3DVP390A",
      "section_id": "01KXR2GFF86JTE76MXTVJJ65K2",
      "name": "Delete Command Example 2",
      "code": "protected override async Task HandleValidatedRequestAsync(\n    DeleteWorkflowsRequest req, CancellationToken ct)\n{\n    var result = await deleteCommand.ExecuteAsync(req.EntityKeys, ct);\n    if (!result.Succeeded)\n    {\n        await SendProblemAsync(result.Error!.Code, result.Error.StatusCode, result.Error.Message, ct);\n        return;\n    }\n\n    foreach (var key in req.EntityKeys)\n        await auditService.LogAsync(\"workflow.deleted\", \"Workflow\", key, new { }, ct);\n\n    await Send.NoContentAsync(ct);\n}",
      "language": "csharp",
      "is_counter": 0,
      "sort_order": 14,
      "created_at": "2026-07-17T12:58:36.9764998+00:00"
    },
    {
      "id": "01KXR2GK6YYV32GYTV127SRGEM",
      "section_id": "01KXR2GFM28DQE80J47QKDGXD4",
      "name": "Soft Delete Command Example 1",
      "code": "public class DeleteActionsCommand(IDbContextFactory<ActionsDbContext> dbContextFactory)\n{\n    public async Task<CommandResult> ExecuteAsync(\n        Guid[] keys, Guid userId, CancellationToken ct = default, ActionsDbContext? db = null)\n    {\n        var shouldDisposeContext = db is null;\n        db ??= await dbContextFactory.CreateDbContextAsync(ct);\n        try\n        {\n            var actions = await db.Actions\n                .Where(a => keys.Contains(a.Id))\n                .ToListAsync(ct);\n\n            if (actions.Count != keys.Length)\n                return CommandResult.Fail(\"ACTION-001\", \"One or more actions not found.\", 404);\n\n            foreach (var action in actions)\n            {\n                action.IsDeleted = true;\n                action.DeletedDate = DateTime.UtcNow;\n                action.DeletedById = userId;\n            }\n\n            await db.SaveChangesAsync(ct);\n            return CommandResult.Success;\n        }\n        finally\n        {\n            if (shouldDisposeContext)\n                await db.DisposeAsync();\n        }\n    }\n}",
      "language": "csharp",
      "is_counter": 0,
      "sort_order": 15,
      "created_at": "2026-07-17T12:58:37.1517425+00:00"
    },
    {
      "id": "01KXR2GKD9P34VHCN3SHK6WCMN",
      "section_id": "01KXR2GFS55PFEJZXBPGDFM160",
      "name": "Lifecycle / Action Commands Example 1",
      "code": "public class ActivateComplianceProfileCommand(\n    IDbContextFactory<ActionsDbContext> dbContextFactory,\n    ILogger<ActivateComplianceProfileCommand> logger)\n{\n    public async Task<CommandResult> ExecuteAsync(\n        Guid profileId, Guid userId,\n        CancellationToken ct, ActionsDbContext? db = null)\n    {\n        var shouldDisposeContext = db is null;\n        db ??= await dbContextFactory.CreateDbContextAsync(ct);\n        try\n        {\n            var profile = await db.ComplianceProfiles\n                .FirstOrDefaultAsync(p => p.Id == profileId, ct);\n\n            if (profile is null)\n                return CommandResult.Fail(\"PROFILE-001\", \"Compliance profile not found.\", 404);\n\n            if (profile.Status != ComplianceProfileStatus.Draft)\n                return CommandResult.Fail(\"PROFILE-002\", \"Profile is not in draft status.\", 422);\n\n            var now = DateTime.UtcNow;\n            profile.Status = ComplianceProfileStatus.Active;\n            profile.ActivatedAt = now;\n            profile.UpdatedDate = now;\n            profile.UpdatedById = userId;\n            await db.SaveChangesAsync(ct);\n            return CommandResult.Success;\n        }\n        finally\n        {\n            if (shouldDisposeContext)\n                await db.DisposeAsync();\n        }\n    }\n}",
      "language": "csharp",
      "is_counter": 0,
      "sort_order": 16,
      "created_at": "2026-07-17T12:58:37.3542582+00:00"
    },
    {
      "id": "01KXR2GKJMEDVS8QRYD7BZEAHJ",
      "section_id": "01KXR2GFS55PFEJZXBPGDFM160",
      "name": "Lifecycle / Action Commands Example 2",
      "code": "protected override async Task HandleValidatedRequestAsync(CancellationToken ct)\n{\n    var id = Route<Guid>(\"id\");\n    var result = await activateCommand.ExecuteAsync(id, UserId, ct);\n    if (!result.Succeeded)\n    {\n        await SendProblemAsync(result.Error!.Code, result.Error.StatusCode, result.Error.Message, ct);\n        return;\n    }\n\n    await auditService.LogAsync(\"compliance_profile.activated\", \"ComplianceProfile\", id,\n        new { }, ct);\n    await Send.NoContentAsync(ct);\n}",
      "language": "csharp",
      "is_counter": 0,
      "sort_order": 17,
      "created_at": "2026-07-17T12:58:37.5264796+00:00"
    },
    {
      "id": "01KXR2GKR4CV8XEEKT7MNGSGJH",
      "section_id": "01KXR2GFS55PFEJZXBPGDFM160",
      "name": "When the caller needs the updated entity state after a lifecycle transition",
      "code": "public class CloneWorkflowCommand(\n    IDbContextFactory<ActionsDbContext> dbContextFactory,\n    WorkflowEntityMapper entityMapper)\n{\n    public async Task<CommandResult<WorkflowDefinition>> ExecuteAsync(\n        Guid sourceId, Guid userId,\n        Guid requestLanguageId, Guid defaultLanguageId,\n        CancellationToken ct, ActionsDbContext? db = null)\n    {\n        var shouldDisposeContext = db is null;\n        db ??= await dbContextFactory.CreateDbContextAsync(ct);\n        try\n        {\n            var source = await db.Workflows\n                .Include(w => w.States)\n                .Include(w => w.Transitions)\n                .FirstOrDefaultAsync(w => w.Id == sourceId, ct);\n\n            if (source is null)\n                return CommandResult<WorkflowDefinition>.Fail(\"WORKFLOW-002\", \"Source workflow not found.\", 404);\n\n            // ... clone logic ...\n\n            await db.SaveChangesAsync(ct);\n            return CommandResult<WorkflowDefinition>.Ok(clonedWorkflow);\n        }\n        finally\n        {\n            if (shouldDisposeContext)\n                await db.DisposeAsync();\n        }\n    }\n}",
      "language": "csharp",
      "is_counter": 0,
      "sort_order": 18,
      "created_at": "2026-07-17T12:58:37.7016433+00:00"
    },
    {
      "id": "01KXR2GKWZ69NWQG54CY59W7AE",
      "section_id": "01KXR2GFS55PFEJZXBPGDFM160",
      "name": "Lifecycle / Action Commands Example 4",
      "code": "protected override async Task HandleValidatedRequestAsync(CancellationToken ct)\n{\n    var id = Route<Guid>(\"id\");\n    var result = await cloneCommand.ExecuteAsync(\n        id, UserId, RequestLanguageId, DefaultLanguageId, ct);\n    if (!result.Succeeded)\n    {\n        await SendProblemAsync(result.Error!.Code, result.Error.StatusCode, result.Error.Message, ct);\n        return;\n    }\n\n    var dto = dtoMapper.Map(result.Value!, RequestLanguageId, DefaultLanguageId);\n    await auditService.LogAsync(\"workflow.cloned\", \"Workflow\", result.Value!.Id,\n        new { SourceId = id }, ct);\n    await Send.CreatedAtAsync<GetWorkflowEndpoint>(\n        new { id = result.Value!.Id }, dto, ct);\n}",
      "language": "csharp",
      "is_counter": 0,
      "sort_order": 19,
      "created_at": "2026-07-17T12:58:37.8564236+00:00"
    },
    {
      "id": "01KXR2GM1WXA0N0D4Y6YS6M5C0",
      "section_id": "01KXR2GFY1EGV74TDR2P34YT69",
      "name": "Transaction Spanning Example 1",
      "code": "public async Task<CommandResult<EntityMapperResult<ActionEntity>>> ExecuteAsync(\n    SaveActionRequest request, Guid userId,\n    Guid requestLanguageId, Guid defaultLanguageId,\n    CancellationToken ct = default, ActionsDbContext? db = null)\n{\n    var shouldDisposeContext = db is null;\n    db ??= await dbContextFactory.CreateDbContextAsync(ct);\n    try\n    {\n        // ... command logic ...\n    }\n    finally\n    {\n        if (shouldDisposeContext)\n            await db.DisposeAsync();\n    }\n}",
      "language": "csharp",
      "is_counter": 0,
      "sort_order": 20,
      "created_at": "2026-07-17T12:58:38.0139540+00:00"
    },
    {
      "id": "01KXR2GM7V8597HR35XEP3379Z",
      "section_id": "01KXR2GFY1EGV74TDR2P34YT69",
      "name": "The caller controls the transaction",
      "code": "await using var db = await dbContextFactory.CreateDbContextAsync(ct);\nawait using var transaction = await db.Database.BeginTransactionAsync(ct);\n\nawait saveCommand.ExecuteAsync(request, userId, requestLanguageId, defaultLanguageId, ct, db);\nawait someOtherCommand.ExecuteAsync(entityId, ct, db);\nawait transaction.CommitAsync(ct);",
      "language": "csharp",
      "is_counter": 0,
      "sort_order": 21,
      "created_at": "2026-07-17T12:58:38.2048905+00:00"
    },
    {
      "id": "01KXR2GMDH76SEWE48Q7DXPNGN",
      "section_id": "01KXR2GG2CFY3Y6D5MHDHVENJP",
      "name": "Logging Example 1",
      "code": "// Information: Business event summaries\nlogger.LogInformation(\"Saved action {ActionId} ({StepCount} steps, {TriggerCount} triggers)\",\n    actionId, stepsToAdd.Count, triggersToAdd.Count);\n\n// Debug: Internal details\nlogger.LogDebug(\"Diffed workflow steps: {Added} added, {Removed} removed\", addedCount, removedCount);\n\n// Warning: Recoverable failures (best-effort side effects)\nlogger.LogWarning(ex, \"Failed to invalidate cache for workflow {WorkflowId}\", workflowId);\n\n// Error: Failures requiring attention\nlogger.LogError(ex, \"Failed to notify subscribers for action {ActionId}\", actionId);",
      "language": "csharp",
      "is_counter": 0,
      "sort_order": 22,
      "created_at": "2026-07-17T12:58:38.3865427+00:00"
    },
    {
      "id": "01KXR2GMM18K7Z56C6BF1BT4M6",
      "section_id": "01KXR2GG6X682ZRSS6SMSKHHRX",
      "name": "Common Mistakes Example 1",
      "code": "// CORRECT: CommandResult<EntityMapperResult<T>> with explicit failure handling\nvar mapResult = await entityMapper.MapAsync(\n    [request], userId, requestLanguageId, defaultLanguageId, ct, db);\nif (mapResult.NewItems.Count == 0 && mapResult.UpdatedItems.Count == 0)\n    return CommandResult<EntityMapperResult<ActionEntity>>.Fail(\"ACTION-001\", \"Not found.\", 404);\n// ... business logic, uniqueness checks return Fail on violation ...\nreturn CommandResult<EntityMapperResult<ActionEntity>>.Ok(mapResult);\n\n// WRONG: Raw EntityMapperResult with ThrowError for expected outcomes\nvar mapResult = await entityMapper.MapAsync(...);\nif (slugExists) ThrowError(\"Slug already exists.\");  // ThrowError is an endpoint method, not available in commands\nreturn mapResult;\n\n// WRONG: SaveResult with boolean flags\npublic async Task<SaveResult> ExecuteAsync(...)\n{\n    return SaveResult.Success(entity.Id);  // No structured result\n}",
      "language": "csharp",
      "is_counter": 1,
      "sort_order": 23,
      "created_at": "2026-07-17T12:58:38.5944893+00:00"
    },
    {
      "id": "01KXR2GMSQA0DRKGJQ63JTPFVJ",
      "section_id": "01KXR2GG6X682ZRSS6SMSKHHRX",
      "name": "Common Mistakes Example 2",
      "code": "// CORRECT: Guid.Empty for create/update detection (Capstone-aligned)\nif (dto.Id == Guid.Empty)\n{\n    // create path — mapper generates new Guid.CreateVersion7()\n}\nelse\n{\n    // update path — mapper loads existing entity\n}\n\n// WRONG: Guid? with null detection\nif (request.Id is null)\n{\n    var entity = request.ToEntity(userId);\n    await db.Actions.AddAsync(entity, ct);\n}\nelse\n{\n    var existing = await db.Actions.FindAsync(request.Id.Value);\n    request.ApplyTo(existing, userId);\n}",
      "language": "csharp",
      "is_counter": 1,
      "sort_order": 24,
      "created_at": "2026-07-17T12:58:38.7761822+00:00"
    },
    {
      "id": "01KXR2GMZDM090326E8GRJET7K",
      "section_id": "01KXR2GG6X682ZRSS6SMSKHHRX",
      "name": "Common Mistakes Example 3",
      "code": "// CORRECT: Injected EntityMapper class returning EntityMapperResult<T>\nvar mapResult = await entityMapper.MapAsync(\n    [dto], userId, requestLanguageId, defaultLanguageId, ct, db);\nvar isNew = mapResult.NewItems.Count > 0;\nawait db.Actions.AddRangeAsync(mapResult.NewItems, ct);\ndb.Actions.UpdateRange(mapResult.UpdatedItems);\n\n// WRONG: Static extension methods — no DI, no EntityMapperResult wrapper\nvar entity = request.ToEntity(userId);          // create\nrequest.ApplyTo(existing, userId);              // update",
      "language": "csharp",
      "is_counter": 1,
      "sort_order": 25,
      "created_at": "2026-07-17T12:58:38.9582268+00:00"
    },
    {
      "id": "01KXR2GN4Z08E0RSAC4AKH45QM",
      "section_id": "01KXR2GG6X682ZRSS6SMSKHHRX",
      "name": "Common Mistakes Example 4",
      "code": "// CORRECT: SaveRequest inherits from DTO (Capstone-aligned)\npublic class SaveActionRequest : ActionDTO\n{\n    // Additional save-specific fields if needed\n    public List<SaveWorkflowStepRequest> Steps { get; set; } = [];\n}\n\n// WRONG: Independent request type duplicating DTO fields\npublic class SaveActionRequest\n{\n    public Guid? Id { get; set; }\n    public string Name { get; set; } = string.Empty;\n    public string Slug { get; set; } = string.Empty;\n    public List<SaveWorkflowStepRequest> Steps { get; set; } = [];\n}",
      "language": "csharp",
      "is_counter": 1,
      "sort_order": 26,
      "created_at": "2026-07-17T12:58:39.1358478+00:00"
    },
    {
      "id": "01KXR2GNAF4BVS3T3YX666F6HB",
      "section_id": "01KXR2GG6X682ZRSS6SMSKHHRX",
      "name": "Common Mistakes Example 5",
      "code": "// CORRECT: ExecuteDeleteAsync — bulk server-side delete, no entity loading\nawait db.WorkflowSteps\n    .Where(s => keys.Contains(s.WorkflowId))\n    .ExecuteDeleteAsync(ct);\n\n// WRONG: Load entities then RemoveRange — unnecessary memory and round trips\nvar steps = await db.WorkflowSteps\n    .Where(s => keys.Contains(s.WorkflowId))\n    .ToListAsync(ct);\ndb.WorkflowSteps.RemoveRange(steps);\nawait db.SaveChangesAsync(ct);",
      "language": "csharp",
      "is_counter": 1,
      "sort_order": 27,
      "created_at": "2026-07-17T12:58:39.3124711+00:00"
    },
    {
      "id": "01KXR2GNEV4NK9YF0SST0D8FZ3",
      "section_id": "01KXR2GG6X682ZRSS6SMSKHHRX",
      "name": "Common Mistakes Example 6",
      "code": "// CORRECT: Delete returns CommandResult, protection checks return Fail\npublic async Task<CommandResult> ExecuteAsync(Guid[] keys, CancellationToken ct)\n{\n    if (protectedEntities.Count > 0)\n        return CommandResult.Fail(\"ENTITY-001\", \"Cannot delete protected entities.\", 422);\n    // ... ExecuteDeleteAsync ...\n    return CommandResult.Success;\n}\n\n// WRONG: Void return with thrown exceptions for expected outcomes\npublic async Task ExecuteAsync(Guid[] keys, CancellationToken ct)\n{\n    if (protectedEntities.Count > 0)\n        throw new ValidationException(\"Cannot delete protected entities.\");\n}\n\n// WRONG: OneOf return for delete commands\npublic async Task<OneOf<Deleted, ValidationFailed>> ExecuteAsync(Guid[] keys, CancellationToken ct)",
      "language": "csharp",
      "is_counter": 1,
      "sort_order": 28,
      "created_at": "2026-07-17T12:58:39.4526523+00:00"
    },
    {
      "id": "01KXR2GNN9B6AWB9KGVWWQY8TG",
      "section_id": "01KXR2GGCS4178YA7PGNR06TVE",
      "name": "File Organization Example 1",
      "code": "Features/Shared/\n└── Results.cs                             # CommandResult, CommandResult<T>, CommandError\n\nFeatures/{Entity}/Shared/Commands/\n├── Save{Entity}Command.cs              # Upsert → CommandResult<EntityMapperResult<T>>\n├── Delete{Entity}Command.cs            # Bulk delete → CommandResult\n├── {Lifecycle}{Entity}Command.cs       # State transition → CommandResult or CommandResult<T>\n└── {Action}{Entity}Command.cs          # Domain operation → CommandResult<T>\n\nFeatures/{Entity}/Shared/Mappers/\n└── {Entity}EntityMapper.cs             # DI-registered mapper returning EntityMapperResult<T>",
      "is_counter": 0,
      "sort_order": 29,
      "created_at": "2026-07-17T12:58:39.6590848+00:00"
    },
    {
      "id": "01KXR2GNVKJJT6PV48XZGG8E94",
      "section_id": "01KXR2GG6X682ZRSS6SMSKHHRX",
      "name": "Direct DbContext constructor breaks transaction composition",
      "description": [
        "Production commands must use IDbContextFactory and an optional shared context parameter; direct scoped DbContext injection prevents callers from composing commands in one transaction and bypasses the retry-safe owned-context pattern."
      ],
      "code": "public class SaveWorkflowCommand(ActionsDbContext dbContext, IAuditService auditService)\n{\n    public async Task<CommandResult> ExecuteAsync(SaveWorkflowRequest request, CancellationToken ct)\n    {\n        dbContext.WorkflowDefinitions.Add(Map(request));\n        await dbContext.SaveChangesAsync(ct);\n\n        // Audit uses another context and cannot roll back with the workflow save.\n        await auditService.LogAsync(\"workflow_definition.created\", \"Workflow\", \"WorkflowDefinition\", request.Id, request.Name, request, ct);\n        return CommandResult.Success;\n    }\n}",
      "language": "csharp",
      "is_counter": 1,
      "sort_order": 30,
      "created_at": "2026-07-17T12:58:39.8614930+00:00"
    }
  ],
  "links": [
    {
      "id": "01KXR35NEW9Q5QQRMAX927NNKV",
      "target_type": "adr",
      "target": "ADR-CORE-0020",
      "rel": "implements",
      "created_at": "2026-07-17T13:10:07.5811508+00:00"
    }
  ],
  "rules": [
    {
      "id": "01KXR2GP116M53TCSD2693YGXY",
      "rule_text": "Use `IDbContextFactory<ActionsDbContext>` in command constructors; never inject scoped `ActionsDbContext` directly in production services.\n",
      "rule_type": "must",
      "sort_order": 0,
      "created_at": "2026-07-17T12:58:40.0341089+00:00"
    },
    {
      "id": "01KXR2GP7DCEZP8ANHK9173T5E",
      "rule_text": "Use the save (upsert) pattern — determine create vs update by `dto.Id == Guid.Empty`",
      "rule_type": "must",
      "sort_order": 1,
      "created_at": "2026-07-17T12:58:40.2385657+00:00"
    },
    {
      "id": "01KXR2GPD0RJBQW7TAY22HPKHM",
      "rule_text": "Use DI-registered `EntityMapper` classes that return `EntityMapperResult<T>` for the mapping step in save commands",
      "rule_type": "must",
      "sort_order": 2,
      "created_at": "2026-07-17T12:58:40.4171997+00:00"
    },
    {
      "id": "01KXR2GPJ86335ZGS5JDG5Y9Z6",
      "rule_text": "Save commands return `CommandResult<EntityMapperResult<T>>` — check `Succeeded` before accessing `Value`",
      "rule_type": "must",
      "sort_order": 3,
      "created_at": "2026-07-17T12:58:40.5870503+00:00"
    },
    {
      "id": "01KXR2GPQF52Q7BJCJJNFD8KQF",
      "rule_text": "Delete commands return `CommandResult` — protection checks return `CommandResult.Fail(...)`",
      "rule_type": "must",
      "sort_order": 4,
      "created_at": "2026-07-17T12:58:40.7523800+00:00"
    },
    {
      "id": "01KXR2GPWMYH7TWFSMZAQ71QDX",
      "rule_text": "Lifecycle/action commands return `CommandResult` or `CommandResult<T>` — expected errors return `Fail(...)`",
      "rule_type": "must",
      "sort_order": 5,
      "created_at": "2026-07-17T12:58:40.9172652+00:00"
    },
    {
      "id": "01KXR2GQ151XBYFJN74414BTN8",
      "rule_text": "Check for empty mapper result on update (entity not found) — return `Fail(404)`",
      "rule_type": "must",
      "sort_order": 6,
      "created_at": "2026-07-17T12:58:41.0625224+00:00"
    },
    {
      "id": "01KXR2GQ6D1KWF6G9PJ219YWNV",
      "rule_text": "Use `SaveRequest : EntityDTO` inheritance — SaveRequest extends the DTO",
      "rule_type": "must",
      "sort_order": 7,
      "created_at": "2026-07-17T12:58:41.2307185+00:00"
    },
    {
      "id": "01KXR2GQAW1PHDY436SKTKTHY7",
      "rule_text": "Call `AddRange`/`UpdateRange` on `EntityMapperResult` lists",
      "rule_type": "must",
      "sort_order": 8,
      "created_at": "2026-07-17T12:58:41.3735310+00:00"
    },
    {
      "id": "01KXR2GQF4GM0Y8754E990MF4K",
      "rule_text": "Wrap `SaveChangesAsync` in try/catch for TOCTOU — return `Fail(409)` on unique constraint violation",
      "rule_type": "must",
      "sort_order": 9,
      "created_at": "2026-07-17T12:58:41.5097911+00:00"
    },
    {
      "id": "01KXR2GQM17SFNW7QAB6N94PFE",
      "rule_text": "Use explicit transactions in delete commands",
      "rule_type": "must",
      "sort_order": 10,
      "created_at": "2026-07-17T12:58:41.6665858+00:00"
    },
    {
      "id": "01KXR2GQSDJR1Q4V3CCF5F5289",
      "rule_text": "Use `ExecuteDeleteAsync` for hard deletes — never load-and-delete with `RemoveRange`",
      "rule_type": "must",
      "sort_order": 11,
      "created_at": "2026-07-17T12:58:41.8385367+00:00"
    },
    {
      "id": "01KXR2GQYEBH2EJM3RKBM4PXM7",
      "rule_text": "Use soft delete (set `ISoftDeletable` fields + `SaveChangesAsync`) for ActionEntity, ActionEvidence, ActionConsultation — never physically delete these entities (ADR-0020)",
      "rule_type": "must",
      "sort_order": 12,
      "created_at": "2026-07-17T12:58:41.9997909+00:00"
    },
    {
      "id": "01KXR2GR4W7E2KEH9RDBX0HBB2",
      "rule_text": "Wrap post-save side effects in individual try/catch blocks (best-effort)",
      "rule_type": "must",
      "sort_order": 13,
      "created_at": "2026-07-17T12:58:42.2049565+00:00"
    },
    {
      "id": "01KXR2GR9V81HJ37EJXHF663B6",
      "rule_text": "Use a public IDbContextFactory<ActionsDbContext> constructor for production command DI; internal ActionsDbContext constructors are allowed only for focused tests.",
      "rule_type": "must",
      "sort_order": 14,
      "created_at": "2026-07-17T12:58:42.3645682+00:00"
    },
    {
      "id": "01KXR2GREFX2KM38E34YT339WB",
      "rule_text": "Use `Guid.CreateVersion7()` for new entity IDs",
      "rule_type": "must",
      "sort_order": 15,
      "created_at": "2026-07-17T12:58:42.5118853+00:00"
    },
    {
      "id": "01KXR2GRKZ33R6DNREE3VNM3YB",
      "rule_text": "Accept ActionsDbContext? dbContext = null after CancellationToken on every DbContext-backed command execution method so callers can compose commands in a shared transaction.",
      "rule_type": "must",
      "sort_order": 16,
      "created_at": "2026-07-17T12:58:42.6885431+00:00"
    },
    {
      "id": "01KXR2GRS5MH3PXNVDE6X0D7FD",
      "rule_text": "Validate referential integrity before save (entity exists, FK targets valid)",
      "rule_type": "should",
      "sort_order": 17,
      "created_at": "2026-07-17T12:58:42.8577082+00:00"
    },
    {
      "id": "01KXR2GRXXQZCKSVKZGKGGTKGX",
      "rule_text": "In owned mode, create the working DbContext inside the EF execution-strategy delegate before beginning an explicit transaction.",
      "rule_type": "must",
      "sort_order": 17,
      "created_at": "2026-07-17T12:58:43.0065625+00:00"
    },
    {
      "id": "01KXR2GS2ZC1RG1EKQ3D5SBRJG",
      "rule_text": "Check system protection (core/system entities) before mutation",
      "rule_type": "should",
      "sort_order": 18,
      "created_at": "2026-07-17T12:58:43.1680195+00:00"
    },
    {
      "id": "01KXR2GS7VN1KB3W3G921280MV",
      "rule_text": "In shared mode, use the supplied DbContext and participate in its current transaction when one exists; do not dispose caller-owned contexts.",
      "rule_type": "must",
      "sort_order": 18,
      "created_at": "2026-07-17T12:58:43.3248267+00:00"
    },
    {
      "id": "01KXR2GSD1EMKFPRZY01QYES1C",
      "rule_text": "Create separate Create/Update commands — use a single Save command",
      "rule_type": "must_not",
      "sort_order": 19,
      "created_at": "2026-07-17T12:58:43.4903116+00:00"
    },
    {
      "id": "01KXR2GSHJ281NFQNBVXH53CX5",
      "rule_text": "Stage audit rows through `IAuditService.LogAsync(..., dbContext)` when the audit entry must commit or roll back with the aggregate mutation.",
      "rule_type": "must",
      "sort_order": 19,
      "created_at": "2026-07-17T12:58:43.6359421+00:00"
    },
    {
      "id": "01KXR2GSPN1F7JX0H5NS8PBTXN",
      "rule_text": "Use static extension method mappers — use DI-registered `EntityMapper` classes",
      "rule_type": "must_not",
      "sort_order": 20,
      "created_at": "2026-07-17T12:58:43.7982888+00:00"
    },
    {
      "id": "01KXR2GSY9MF1TMB3CZMBQJ3NP",
      "rule_text": "Query data for display — that's the [Query pattern](queries.md)",
      "rule_type": "must_not",
      "sort_order": 21,
      "created_at": "2026-07-17T12:58:44.0427357+00:00"
    },
    {
      "id": "01KXR2GT55YSKFH3SBMH9EEVV7",
      "rule_text": "Publish events directly — endpoints handle side effects",
      "rule_type": "must_not",
      "sort_order": 22,
      "created_at": "2026-07-17T12:58:44.2648944+00:00"
    },
    {
      "id": "01KXR2GTAS00000B2ZRWRS94BD",
      "rule_text": "Write `AuditLog` entities directly; use `IAuditService` and pass the shared DbContext when the audit entry is transactional.",
      "rule_type": "must_not",
      "sort_order": 23,
      "created_at": "2026-07-17T12:58:44.4425172+00:00"
    },
    {
      "id": "01KXR2GTFDWS77GHERJMW3VE9G",
      "rule_text": "Use `SaveResult` with boolean flags — use `CommandResult<EntityMapperResult<T>>` for saves",
      "rule_type": "must_not",
      "sort_order": 24,
      "created_at": "2026-07-17T12:58:44.5906079+00:00"
    },
    {
      "id": "01KXR2GTKVY8KHV2JBWC9R2Q2W",
      "rule_text": "Use `OneOf<>` for any command return type — use `CommandResult` variants",
      "rule_type": "must_not",
      "sort_order": 25,
      "created_at": "2026-07-17T12:58:44.7325551+00:00"
    },
    {
      "id": "01KXR2GTS1APKX74H4BD1BWM5B",
      "rule_text": "Throw exceptions for expected domain outcomes (not found, protected, invalid state, uniqueness conflict) — use `CommandResult.Fail(...)`",
      "rule_type": "must_not",
      "sort_order": 26,
      "created_at": "2026-07-17T12:58:44.8981291+00:00"
    },
    {
      "id": "01KXR2GTYC1S4PK0HJYJXTXVXG",
      "rule_text": "Use `Guid?` with null to signal create — use `Guid.Empty` (`dto.Id == Guid.Empty`)",
      "rule_type": "must_not",
      "sort_order": 27,
      "created_at": "2026-07-17T12:58:45.0691985+00:00"
    },
    {
      "id": "01KXR2GV4H56E6V7X4Z9ZKXHJ2",
      "rule_text": "Use independent `SaveRequest` types — inherit from the entity DTO",
      "rule_type": "must_not",
      "sort_order": 28,
      "created_at": "2026-07-17T12:58:45.2667465+00:00"
    },
    {
      "id": "01KXR2GV9Y05M3BPK93W8VTRYV",
      "rule_text": "Open a transaction outside EF's execution strategy in owned mode when retries are enabled.",
      "rule_type": "must_not",
      "sort_order": 29,
      "created_at": "2026-07-17T12:58:45.4398251+00:00"
    }
  ],
  "sections": [
    {
      "id": "01KXR2GEVEAA5878T050X9HFBE",
      "title": "Command Types",
      "content": [
        "| Type | Purpose | Return Type | Example |",
        "|------|---------|----|---------|",
        "| **Save** | Upsert (create or update) | `CommandResult<EntityMapperResult<T>>` | `SaveActionCommand` |",
        "| **Delete** | Bulk remove by keys | `CommandResult` | `DeleteWorkflowCommand` |",
        "| **Lifecycle** | State machine transition | `CommandResult` or `CommandResult<T>` | `ActivateComplianceProfileCommand` |",
        "| **Action** | Domain-specific operation | `CommandResult<T>` | `CloneWorkflowCommand` |",
        "",
        "```",
        "┌───────────────────┐  ┌───────────────────┐  ┌───────────────────┐",
        "│  Save{Entity}     │  │  Delete{Entity}   │  │  {Action}{Entity} │",
        "│  Command          │  │  Command          │  │  Command          │",
        "├───────────────────┤  ├───────────────────┤  ├───────────────────┤",
        "│ Upsert (Empty?)   │  │ Bulk by Guid[]    │  │ State transition  │",
        "│ EntityMapper (DI) │  │ ExecuteDeleteAsync│  │ Cascade effects   │",
        "│ CommandResult<    │  │ Explicit tx       │  │ Side effects      │",
        "│ EntityMapperResult│  │ Returns           │  │ Returns           │",
        "│ <T>>              │  │  CommandResult    │  │  CommandResult<T> │",
        "└───────────────────┘  └───────────────────┘  └───────────────────┘",
        "```"
      ],
      "section_type": "narrative",
      "sort_order": 0,
      "heading_level": 2,
      "created_at": "2026-07-17T12:58:32.6878315+00:00"
    },
    {
      "id": "01KXR2GF0MBXVK7DEMPBA1EJ5A",
      "title": "Shared Result Types",
      "content": [
        "All non-save commands return `CommandResult` or `CommandResult<T>`. These types live in `Features/Shared/Results.cs`:",
        "",
        "```csharp",
        "/// <summary>",
        "/// Structured error payload — maps directly to SendProblemAsync parameters.",
        "/// </summary>",
        "public readonly record struct CommandError(string Code, string Message, int StatusCode = 400);",
        "",
        "/// <summary>",
        "/// Result for commands that don't return data (delete, simple lifecycle).",
        "/// </summary>",
        "public record CommandResult",
        "{",
        "    public CommandError? Error { get; init; }",
        "    public bool Succeeded => Error is null;",
        "",
        "    public static readonly CommandResult Success = new();",
        "    public static CommandResult Fail(string code, string message, int statusCode = 400)",
        "        => new() { Error = new(code, message, statusCode) };",
        "}",
        "",
        "/// <summary>",
        "/// Result for commands that return data (lifecycle with response DTO, action commands).",
        "/// </summary>",
        "public record CommandResult<T> : CommandResult",
        "{",
        "    public T? Value { get; init; }",
        "",
        "    public static CommandResult<T> Ok(T value) => new() { Value = value };",
        "    // Inherits Fail() from base — returns CommandResult<T> via covariance",
        "    public new static CommandResult<T> Fail(string code, string message, int statusCode = 400)",
        "        => new() { Error = new(code, message, statusCode) };",
        "}",
        "```",
        "",
        "### Design Rationale",
        "",
        "| Concern | How CommandResult addresses it |",
        "|---------|-------------------------------|",
        "| Single return type per command | Every command returns one type — no discriminated unions, no multi-path matching |",
        "| No boolean flag ambiguity | `Succeeded` is derived from `Error is null` — single source of truth |",
        "| No exceptions for expected outcomes | NotFound, protection violations, invalid state → `CommandResult.Fail(...)` |",
        "| Self-documenting errors | `CommandError` carries Code, Message, and StatusCode — maps directly to RFC 7807 |",
        "| Simple endpoint consumption | `if (!result.Succeeded)` → `SendProblemAsync(...)` — no `Match()` ceremony |",
        "",
        "### Error Code Convention",
        "",
        "Error codes follow the format `{MODULE}-{NNN}` where:",
        "- `{MODULE}` matches the feature folder name in UPPER-SNAKE-CASE (e.g., `ACTION`, `WORKFLOW`, `COMPLIANCE-PROFILE`)",
        "- `{NNN}` is a zero-padded sequential number within the module, starting at `001`",
        "",
        "| Code | Meaning | HTTP Status |",
        "|------|---------|-------------|",
        "| `{MODULE}-001` | Entity not found | 404 |",
        "| `{MODULE}-002` | Uniqueness conflict (slug, code) | 409 |",
        "| `{MODULE}-003` | Protection violation (system entity) | 422 |",
        "| `{MODULE}-004+` | Feature-specific business rules | 422 |",
        "",
        "Reserve `001`–`003` for the standard error types above. Feature-specific errors start at `004`. Each command documents its error codes in a comment block:",
        "",
        "```csharp",
        "// Error codes:",
        "// ACTION-001: Action not found (404)",
        "// ACTION-002: Slug already exists (409)",
        "// ACTION-003: Cannot modify protected action (422)",
        "// ACTION-004: Action has active workflows — cannot deactivate (422)",
        "```",
        "",
        "Error codes must be unique within a module. They are used for programmatic error handling on the frontend and appear in RFC 7807 problem details responses.",
        "",
        "### When to use exceptions vs CommandResult",
        "",
        "| Scenario | Use |",
        "|----------|-----|",
        "| Entity not found | `CommandResult.Fail(\"ENTITY-001\", \"...\", 404)` |",
        "| Protection check (system entity) | `CommandResult.Fail(\"ENTITY-002\", \"...\", 422)` |",
        "| Invalid state transition | `CommandResult.Fail(\"ENTITY-003\", \"...\", 422)` |",
        "| Business rule violation | `CommandResult.Fail(\"ENTITY-004\", \"...\", 422)` |",
        "| Uniqueness conflict (slug/code) | `CommandResult.Fail(\"ENTITY-005\", \"...\", 409)` |",
        "| TOCTOU unique constraint race | `CommandResult.Fail(...)` inside `catch (DbUpdateException)` |",
        "| Unhandled/unexpected failure | Let exception propagate — ProblemDetailsService handles it |",
        "",
        "**Every expected domain outcome uses `CommandResult.Fail()`** — including save commands. The only exceptions that propagate are genuinely unexpected failures (database connectivity, serialization errors, etc.)."
      ],
      "section_type": "narrative",
      "sort_order": 1,
      "heading_level": 2,
      "created_at": "2026-07-17T12:58:32.8530970+00:00"
    },
    {
      "id": "01KXR2GF58M33JPYBE87DZ9A13",
      "title": "Mapper vs Command Boundary",
      "content": [
        "The EntityMapper is a **pure DTO-to-Entity transformer**. The Command owns **all business logic**. This boundary is non-negotiable — see [entity-mapper.md](entity-mapper.md) for the full mapper pattern.",
        "",
        "**The mapper does:**",
        "- Entity resolution (find by ID, business key fallback)",
        "- Create vs update detection (`Guid.Empty` = create)",
        "- DTO field to entity field mapping",
        "- Audit fields (CreatedDate/CreatedById, UpdatedDate/UpdatedById)",
        "- Translation handling (AddOrUpdateEntityTranslation via TranslationService)",
        "",
        "**The command does (everything else):**",
        "- Call the mapper, receive `EntityMapperResult<T>`",
        "- `AddRange(result.NewItems)` for new entities",
        "- Business rules: uniqueness checks, guards, permission checks",
        "- Cross-entity operations: create related entities",
        "- Child collection diffing (aggregate root management)",
        "- `SaveChangesAsync` with TOCTOU catch on unique constraints",
        "- Post-save side effects (Redis invalidation, audit logging)",
        "",
        "### Standard Save Command Flow",
        "",
        "```",
        "1. var mapResult = entityMapper.MapAsync(dtoList, userId, requestLanguageId, defaultLanguageId, ct, db)",
        "2. if empty result (no NewItems, no UpdatedItems) → return Fail(404)",
        "3. if (isNew) → db.AddRange(mapResult.NewItems)",
        "4. Business logic (uniqueness check → Fail(409), guards → Fail(422), cross-entity ops)",
        "5. try { SaveChangesAsync } catch { TOCTOU → Fail(409) }",
        "6. Post-save side effects (audit, cache invalidation)",
        "7. return Ok(mapResult)",
        "```"
      ],
      "section_type": "comparison",
      "sort_order": 2,
      "heading_level": 2,
      "created_at": "2026-07-17T12:58:33.0012354+00:00"
    },
    {
      "id": "01KXR2GFAAF7H9D38RYFZKZ3Z5",
      "title": "Save Command (Primary Pattern)",
      "content": [
        "The save command is the standard write pattern. A single command handles both insert and update, returns `CommandResult<EntityMapperResult<T>>` or a feature-specific command result, and follows the shared DbContext contract from ADR-CORE-0027.",
        "",
        "```csharp",
        "public class SaveActionCommand",
        "{",
        "    private readonly IDbContextFactory<ActionsDbContext>? dbContextFactory;",
        "    private readonly ActionsDbContext? defaultDbContext;",
        "    private readonly ActionEntityMapper entityMapper;",
        "",
        "    public SaveActionCommand(",
        "        IDbContextFactory<ActionsDbContext> dbContextFactory,",
        "        ActionEntityMapper entityMapper)",
        "    {",
        "        this.dbContextFactory = dbContextFactory;",
        "        this.entityMapper = entityMapper;",
        "    }",
        "",
        "    internal SaveActionCommand(ActionsDbContext dbContext, ActionEntityMapper entityMapper)",
        "    {",
        "        defaultDbContext = dbContext;",
        "        this.entityMapper = entityMapper;",
        "    }",
        "",
        "    public async Task<CommandResult<EntityMapperResult<ActionEntity>>> ExecuteAsync(",
        "        SaveActionRequest request,",
        "        Guid userId,",
        "        CancellationToken ct = default,",
        "        ActionsDbContext? dbContext = null)",
        "    {",
        "        var sharedDbContext = dbContext ?? defaultDbContext;",
        "        if (sharedDbContext is not null)",
        "        {",
        "            return await ExecuteWithDbContextAsync(",
        "                request,",
        "                userId,",
        "                sharedDbContext,",
        "                ownsTransaction: sharedDbContext.Database.CurrentTransaction is null,",
        "                ct);",
        "        }",
        "",
        "        if (dbContextFactory is null)",
        "        {",
        "            throw new InvalidOperationException(\"A DbContext factory is required when no shared context is supplied.\");",
        "        }",
        "",
        "        await using var strategyDbContext = await dbContextFactory.CreateDbContextAsync(ct);",
        "        var strategy = strategyDbContext.Database.CreateExecutionStrategy();",
        "        return await strategy.ExecuteAsync(async () =>",
        "        {",
        "            await using var ownedDbContext = await dbContextFactory.CreateDbContextAsync(ct);",
        "            return await ExecuteWithDbContextAsync(",
        "                request,",
        "                userId,",
        "                ownedDbContext,",
        "                ownsTransaction: true,",
        "                ct);",
        "        });",
        "    }",
        "}",
        "```",
        "",
        "Commands that do not open explicit transactions may use `DbContextFactoryExtensions.ExecuteWithDbContextAsync` directly. Commands that open transactions use the explicit owned/shared branch so owned mode can run inside the EF execution strategy and shared mode can participate in the caller's current transaction.",
        ""
      ],
      "section_type": "narrative",
      "sort_order": 3,
      "heading_level": 2,
      "created_at": "2026-07-17T12:58:33.1631671+00:00"
    },
    {
      "id": "01KXR2GFF86JTE76MXTVJJ65K2",
      "title": "Delete Command",
      "content": [
        "Delete commands accept `Guid[] keys` for bulk deletion using `ExecuteDeleteAsync`. They return `CommandResult` — protection checks return `CommandResult.Fail(...)` instead of throwing. Explicit transactions prevent partial deletes. Like save and lifecycle commands, they accept an optional `ActionsDbContext? db = null` for transaction spanning.",
        "",
        "```csharp",
        "public class DeleteWorkflowCommand(IDbContextFactory<ActionsDbContext> dbContextFactory)",
        "{",
        "    public async Task<CommandResult> ExecuteAsync(",
        "        Guid[] keys, CancellationToken ct = default, ActionsDbContext? db = null)",
        "    {",
        "        var shouldDisposeContext = db is null;",
        "        db ??= await dbContextFactory.CreateDbContextAsync(ct);",
        "        try",
        "        {",
        "            // Protection check — returns structured error",
        "            var protectedWorkflows = await db.Workflows",
        "                .AsNoTracking()",
        "                .Where(w => keys.Contains(w.Id) && w.IsSystemProtected)",
        "                .Select(w => w.Name)",
        "                .ToListAsync(ct);",
        "",
        "            if (protectedWorkflows.Count > 0)",
        "                return CommandResult.Fail(\"WORKFLOW-001\",",
        "                    $\"Cannot delete protected workflows: {string.Join(\", \", protectedWorkflows)}\", 422);",
        "",
        "            // Explicit transaction — prevents partial deletes on failure",
        "            await using var tx = await db.Database.BeginTransactionAsync(ct);",
        "",
        "            await db.WorkflowSteps",
        "                .Where(s => keys.Contains(s.WorkflowId))",
        "                .ExecuteDeleteAsync(ct);",
        "",
        "            await db.WorkflowTriggers",
        "                .Where(t => keys.Contains(t.WorkflowId))",
        "                .ExecuteDeleteAsync(ct);",
        "",
        "            await db.Workflows",
        "                .Where(w => keys.Contains(w.Id))",
        "                .ExecuteDeleteAsync(ct);",
        "",
        "            await tx.CommitAsync(ct);",
        "            return CommandResult.Success;",
        "        }",
        "        finally",
        "        {",
        "            if (shouldDisposeContext)",
        "                await db.DisposeAsync();",
        "        }",
        "    }",
        "}",
        "```",
        "",
        "### Delete Endpoint Consumption",
        "",
        "```csharp",
        "protected override async Task HandleValidatedRequestAsync(",
        "    DeleteWorkflowsRequest req, CancellationToken ct)",
        "{",
        "    var result = await deleteCommand.ExecuteAsync(req.EntityKeys, ct);",
        "    if (!result.Succeeded)",
        "    {",
        "        await SendProblemAsync(result.Error!.Code, result.Error.StatusCode, result.Error.Message, ct);",
        "        return;",
        "    }",
        "",
        "    foreach (var key in req.EntityKeys)",
        "        await auditService.LogAsync(\"workflow.deleted\", \"Workflow\", key, new { }, ct);",
        "",
        "    await Send.NoContentAsync(ct);",
        "}",
        "```"
      ],
      "section_type": "narrative",
      "sort_order": 4,
      "heading_level": 2,
      "created_at": "2026-07-17T12:58:33.3216532+00:00"
    },
    {
      "id": "01KXR2GFM28DQE80J47QKDGXD4",
      "title": "Soft Delete Command",
      "content": [
        "Entities implementing `ISoftDeletable` (ActionEntity, ActionEvidence, ActionConsultation) are never physically deleted. Delete commands set `IsDeleted`, `DeletedDate`, and `DeletedById` instead of calling `ExecuteDeleteAsync`. The EF global query filter (`HasQueryFilter(e => !e.IsDeleted)`) excludes them from normal queries.",
        "",
        "```csharp",
        "public class DeleteActionsCommand(IDbContextFactory<ActionsDbContext> dbContextFactory)",
        "{",
        "    public async Task<CommandResult> ExecuteAsync(",
        "        Guid[] keys, Guid userId, CancellationToken ct = default, ActionsDbContext? db = null)",
        "    {",
        "        var shouldDisposeContext = db is null;",
        "        db ??= await dbContextFactory.CreateDbContextAsync(ct);",
        "        try",
        "        {",
        "            var actions = await db.Actions",
        "                .Where(a => keys.Contains(a.Id))",
        "                .ToListAsync(ct);",
        "",
        "            if (actions.Count != keys.Length)",
        "                return CommandResult.Fail(\"ACTION-001\", \"One or more actions not found.\", 404);",
        "",
        "            foreach (var action in actions)",
        "            {",
        "                action.IsDeleted = true;",
        "                action.DeletedDate = DateTime.UtcNow;",
        "                action.DeletedById = userId;",
        "            }",
        "",
        "            await db.SaveChangesAsync(ct);",
        "            return CommandResult.Success;",
        "        }",
        "        finally",
        "        {",
        "            if (shouldDisposeContext)",
        "                await db.DisposeAsync();",
        "        }",
        "    }",
        "}",
        "```",
        "",
        "**Key differences from hard delete:**",
        "- Loads entities (required to set `ISoftDeletable` fields) — no `ExecuteDeleteAsync`",
        "- Uses `SaveChangesAsync` (audit interceptor records the change)",
        "- No explicit transaction needed — single `SaveChangesAsync` is already atomic",
        "- To query including soft-deleted records (admin restore, audit views), use `IgnoreQueryFilters()`",
        "",
        "See ADR-0020 for when to use soft delete vs hard delete."
      ],
      "section_type": "narrative",
      "sort_order": 5,
      "heading_level": 2,
      "created_at": "2026-07-17T12:58:33.4754787+00:00"
    },
    {
      "id": "01KXR2GFS55PFEJZXBPGDFM160",
      "title": "Lifecycle / Action Commands",
      "content": [
        "These handle domain-specific operations that don't fit the save/delete pattern. They use the optional `ActionsDbContext? db = null` parameter for transaction spanning and return `CommandResult` (no data) or `CommandResult<T>` (with data).",
        "",
        "### Without Response Data (`CommandResult`)",
        "",
        "```csharp",
        "public class ActivateComplianceProfileCommand(",
        "    IDbContextFactory<ActionsDbContext> dbContextFactory,",
        "    ILogger<ActivateComplianceProfileCommand> logger)",
        "{",
        "    public async Task<CommandResult> ExecuteAsync(",
        "        Guid profileId, Guid userId,",
        "        CancellationToken ct, ActionsDbContext? db = null)",
        "    {",
        "        var shouldDisposeContext = db is null;",
        "        db ??= await dbContextFactory.CreateDbContextAsync(ct);",
        "        try",
        "        {",
        "            var profile = await db.ComplianceProfiles",
        "                .FirstOrDefaultAsync(p => p.Id == profileId, ct);",
        "",
        "            if (profile is null)",
        "                return CommandResult.Fail(\"PROFILE-001\", \"Compliance profile not found.\", 404);",
        "",
        "            if (profile.Status != ComplianceProfileStatus.Draft)",
        "                return CommandResult.Fail(\"PROFILE-002\", \"Profile is not in draft status.\", 422);",
        "",
        "            var now = DateTime.UtcNow;",
        "            profile.Status = ComplianceProfileStatus.Active;",
        "            profile.ActivatedAt = now;",
        "            profile.UpdatedDate = now;",
        "            profile.UpdatedById = userId;",
        "            await db.SaveChangesAsync(ct);",
        "            return CommandResult.Success;",
        "        }",
        "        finally",
        "        {",
        "            if (shouldDisposeContext)",
        "                await db.DisposeAsync();",
        "        }",
        "    }",
        "}",
        "```",
        "",
        "### Lifecycle Endpoint Consumption (no data)",
        "",
        "```csharp",
        "protected override async Task HandleValidatedRequestAsync(CancellationToken ct)",
        "{",
        "    var id = Route<Guid>(\"id\");",
        "    var result = await activateCommand.ExecuteAsync(id, UserId, ct);",
        "    if (!result.Succeeded)",
        "    {",
        "        await SendProblemAsync(result.Error!.Code, result.Error.StatusCode, result.Error.Message, ct);",
        "        return;",
        "    }",
        "",
        "    await auditService.LogAsync(\"compliance_profile.activated\", \"ComplianceProfile\", id,",
        "        new { }, ct);",
        "    await Send.NoContentAsync(ct);",
        "}",
        "```",
        "",
        "### With Response Data (`CommandResult<T>`)",
        "",
        "When the caller needs the updated entity state after a lifecycle transition:",
        "",
        "```csharp",
        "public class CloneWorkflowCommand(",
        "    IDbContextFactory<ActionsDbContext> dbContextFactory,",
        "    WorkflowEntityMapper entityMapper)",
        "{",
        "    public async Task<CommandResult<WorkflowDefinition>> ExecuteAsync(",
        "        Guid sourceId, Guid userId,",
        "        Guid requestLanguageId, Guid defaultLanguageId,",
        "        CancellationToken ct, ActionsDbContext? db = null)",
        "    {",
        "        var shouldDisposeContext = db is null;",
        "        db ??= await dbContextFactory.CreateDbContextAsync(ct);",
        "        try",
        "        {",
        "            var source = await db.Workflows",
        "                .Include(w => w.States)",
        "                .Include(w => w.Transitions)",
        "                .FirstOrDefaultAsync(w => w.Id == sourceId, ct);",
        "",
        "            if (source is null)",
        "                return CommandResult<WorkflowDefinition>.Fail(\"WORKFLOW-002\", \"Source workflow not found.\", 404);",
        "",
        "            // ... clone logic ...",
        "",
        "            await db.SaveChangesAsync(ct);",
        "            return CommandResult<WorkflowDefinition>.Ok(clonedWorkflow);",
        "        }",
        "        finally",
        "        {",
        "            if (shouldDisposeContext)",
        "                await db.DisposeAsync();",
        "        }",
        "    }",
        "}",
        "```",
        "",
        "### Lifecycle Endpoint Consumption (with data)",
        "",
        "```csharp",
        "protected override async Task HandleValidatedRequestAsync(CancellationToken ct)",
        "{",
        "    var id = Route<Guid>(\"id\");",
        "    var result = await cloneCommand.ExecuteAsync(",
        "        id, UserId, RequestLanguageId, DefaultLanguageId, ct);",
        "    if (!result.Succeeded)",
        "    {",
        "        await SendProblemAsync(result.Error!.Code, result.Error.StatusCode, result.Error.Message, ct);",
        "        return;",
        "    }",
        "",
        "    var dto = dtoMapper.Map(result.Value!, RequestLanguageId, DefaultLanguageId);",
        "    await auditService.LogAsync(\"workflow.cloned\", \"Workflow\", result.Value!.Id,",
        "        new { SourceId = id }, ct);",
        "    await Send.CreatedAtAsync<GetWorkflowEndpoint>(",
        "        new { id = result.Value!.Id }, dto, ct);",
        "}",
        "```"
      ],
      "section_type": "narrative",
      "sort_order": 6,
      "heading_level": 2,
      "created_at": "2026-07-17T12:58:33.6388271+00:00"
    },
    {
      "id": "01KXR2GFY1EGV74TDR2P34YT69",
      "title": "DbContext Lifetime and Transaction Spanning",
      "content": [
        "Commands use two DbContext modes:",
        "",
        "1. Owned mode: the command creates a short-lived `ActionsDbContext` from `IDbContextFactory<ActionsDbContext>` and owns persistence, transaction, retry strategy, and disposal.",
        "2. Shared mode: the caller passes `ActionsDbContext? dbContext` so multiple commands or queries can participate in one caller-owned context and transaction.",
        "",
        "The public command constructor injects `IDbContextFactory<ActionsDbContext>`. Commands must not inject scoped `ActionsDbContext` directly. Tests may use an internal constructor with a provided context, but production registration stays factory-based.",
        "",
        "Every DbContext-backed command accepts the optional context after the cancellation token:",
        "",
        "```csharp",
        "public Task<CommandResult<EntityMapperResult<WorkflowDefinition>>> ExecuteAsync(",
        "    SaveWorkflowRequest request,",
        "    Guid userId,",
        "    Guid requestLanguageId,",
        "    Guid defaultLanguageId,",
        "    CancellationToken ct = default,",
        "    ActionsDbContext? dbContext = null)",
        "```",
        "",
        "Owned mode must run explicit transactions through EF Core's execution strategy. Create a separate strategy context, then create the working context inside the retry delegate so retries do not reuse a failed DbContext. Shared mode must not create or dispose the context. If the caller already opened a transaction, the command participates in it; otherwise the command may open and commit its own transaction on the supplied context when it owns the operation boundary.",
        ""
      ],
      "section_type": "narrative",
      "sort_order": 7,
      "heading_level": 2,
      "created_at": "2026-07-17T12:58:33.7939828+00:00"
    },
    {
      "id": "01KXR2GG2CFY3Y6D5MHDHVENJP",
      "title": "Logging",
      "content": [
        "```csharp",
        "// Information: Business event summaries",
        "logger.LogInformation(\"Saved action {ActionId} ({StepCount} steps, {TriggerCount} triggers)\",",
        "    actionId, stepsToAdd.Count, triggersToAdd.Count);",
        "",
        "// Debug: Internal details",
        "logger.LogDebug(\"Diffed workflow steps: {Added} added, {Removed} removed\", addedCount, removedCount);",
        "",
        "// Warning: Recoverable failures (best-effort side effects)",
        "logger.LogWarning(ex, \"Failed to invalidate cache for workflow {WorkflowId}\", workflowId);",
        "",
        "// Error: Failures requiring attention",
        "logger.LogError(ex, \"Failed to notify subscribers for action {ActionId}\", actionId);",
        "```"
      ],
      "section_type": "narrative",
      "sort_order": 8,
      "heading_level": 2,
      "created_at": "2026-07-17T12:58:33.9339873+00:00"
    },
    {
      "id": "01KXR2GG6X682ZRSS6SMSKHHRX",
      "title": "Common Mistakes",
      "content": [
        "### Save command returns CommandResult wrapping EntityMapperResult",
        "",
        "```csharp",
        "// CORRECT: CommandResult<EntityMapperResult<T>> with explicit failure handling",
        "var mapResult = await entityMapper.MapAsync(",
        "    [request], userId, requestLanguageId, defaultLanguageId, ct, db);",
        "if (mapResult.NewItems.Count == 0 && mapResult.UpdatedItems.Count == 0)",
        "    return CommandResult<EntityMapperResult<ActionEntity>>.Fail(\"ACTION-001\", \"Not found.\", 404);",
        "// ... business logic, uniqueness checks return Fail on violation ...",
        "return CommandResult<EntityMapperResult<ActionEntity>>.Ok(mapResult);",
        "",
        "// WRONG: Raw EntityMapperResult with ThrowError for expected outcomes",
        "var mapResult = await entityMapper.MapAsync(...);",
        "if (slugExists) ThrowError(\"Slug already exists.\");  // ThrowError is an endpoint method, not available in commands",
        "return mapResult;",
        "",
        "// WRONG: SaveResult with boolean flags",
        "public async Task<SaveResult> ExecuteAsync(...)",
        "{",
        "    return SaveResult.Success(entity.Id);  // No structured result",
        "}",
        "```",
        "",
        "### Guid.Empty vs Guid?",
        "",
        "```csharp",
        "// CORRECT: Guid.Empty for create/update detection (Capstone-aligned)",
        "if (dto.Id == Guid.Empty)",
        "{",
        "    // create path — mapper generates new Guid.CreateVersion7()",
        "}",
        "else",
        "{",
        "    // update path — mapper loads existing entity",
        "}",
        "",
        "// WRONG: Guid? with null detection",
        "if (request.Id is null)",
        "{",
        "    var entity = request.ToEntity(userId);",
        "    await db.Actions.AddAsync(entity, ct);",
        "}",
        "else",
        "{",
        "    var existing = await db.Actions.FindAsync(request.Id.Value);",
        "    request.ApplyTo(existing, userId);",
        "}",
        "```",
        "",
        "### DI-registered EntityMapper vs extension method mappers",
        "",
        "```csharp",
        "// CORRECT: Injected EntityMapper class returning EntityMapperResult<T>",
        "var mapResult = await entityMapper.MapAsync(",
        "    [dto], userId, requestLanguageId, defaultLanguageId, ct, db);",
        "var isNew = mapResult.NewItems.Count > 0;",
        "await db.Actions.AddRangeAsync(mapResult.NewItems, ct);",
        "db.Actions.UpdateRange(mapResult.UpdatedItems);",
        "",
        "// WRONG: Static extension methods — no DI, no EntityMapperResult wrapper",
        "var entity = request.ToEntity(userId);          // create",
        "request.ApplyTo(existing, userId);              // update",
        "```",
        "",
        "### SaveRequest inherits DTO vs independent SaveRequest",
        "",
        "```csharp",
        "// CORRECT: SaveRequest inherits from DTO (Capstone-aligned)",
        "public class SaveActionRequest : ActionDTO",
        "{",
        "    // Additional save-specific fields if needed",
        "    public List<SaveWorkflowStepRequest> Steps { get; set; } = [];",
        "}",
        "",
        "// WRONG: Independent request type duplicating DTO fields",
        "public class SaveActionRequest",
        "{",
        "    public Guid? Id { get; set; }",
        "    public string Name { get; set; } = string.Empty;",
        "    public string Slug { get; set; } = string.Empty;",
        "    public List<SaveWorkflowStepRequest> Steps { get; set; } = [];",
        "}",
        "```",
        "",
        "### ExecuteDeleteAsync vs RemoveRange",
        "",
        "```csharp",
        "// CORRECT: ExecuteDeleteAsync — bulk server-side delete, no entity loading",
        "await db.WorkflowSteps",
        "    .Where(s => keys.Contains(s.WorkflowId))",
        "    .ExecuteDeleteAsync(ct);",
        "",
        "// WRONG: Load entities then RemoveRange — unnecessary memory and round trips",
        "var steps = await db.WorkflowSteps",
        "    .Where(s => keys.Contains(s.WorkflowId))",
        "    .ToListAsync(ct);",
        "db.WorkflowSteps.RemoveRange(steps);",
        "await db.SaveChangesAsync(ct);",
        "```",
        "",
        "### Delete returns CommandResult, not void or OneOf",
        "",
        "```csharp",
        "// CORRECT: Delete returns CommandResult, protection checks return Fail",
        "public async Task<CommandResult> ExecuteAsync(Guid[] keys, CancellationToken ct)",
        "{",
        "    if (protectedEntities.Count > 0)",
        "        return CommandResult.Fail(\"ENTITY-001\", \"Cannot delete protected entities.\", 422);",
        "    // ... ExecuteDeleteAsync ...",
        "    return CommandResult.Success;",
        "}",
        "",
        "// WRONG: Void return with thrown exceptions for expected outcomes",
        "public async Task ExecuteAsync(Guid[] keys, CancellationToken ct)",
        "{",
        "    if (protectedEntities.Count > 0)",
        "        throw new ValidationException(\"Cannot delete protected entities.\");",
        "}",
        "",
        "// WRONG: OneOf return for delete commands",
        "public async Task<OneOf<Deleted, ValidationFailed>> ExecuteAsync(Guid[] keys, CancellationToken ct)",
        "```"
      ],
      "section_type": "narrative",
      "sort_order": 9,
      "heading_level": 2,
      "created_at": "2026-07-17T12:58:34.0785044+00:00"
    },
    {
      "id": "01KXR2GGCS4178YA7PGNR06TVE",
      "title": "File Organization",
      "content": [
        "```",
        "Features/Shared/",
        "└── Results.cs                             # CommandResult, CommandResult<T>, CommandError",
        "",
        "Features/{Entity}/Shared/Commands/",
        "├── Save{Entity}Command.cs              # Upsert → CommandResult<EntityMapperResult<T>>",
        "├── Delete{Entity}Command.cs            # Bulk delete → CommandResult",
        "├── {Lifecycle}{Entity}Command.cs       # State transition → CommandResult or CommandResult<T>",
        "└── {Action}{Entity}Command.cs          # Domain operation → CommandResult<T>",
        "",
        "Features/{Entity}/Shared/Mappers/",
        "└── {Entity}EntityMapper.cs             # DI-registered mapper returning EntityMapperResult<T>",
        "```"
      ],
      "section_type": "narrative",
      "sort_order": 10,
      "heading_level": 2,
      "created_at": "2026-07-17T12:58:34.2667687+00:00"
    },
    {
      "id": "01KXR2GGHX2R1X53XMGQWW16Y3",
      "title": "Rules",
      "content": [
        "### MUST",
        "",
        "1. Use `IDbContextFactory<ActionsDbContext>` in production command constructors; never inject scoped `ActionsDbContext` directly in production services.",
        "2. Accept `ActionsDbContext? dbContext = null` after `CancellationToken` on every DbContext-backed command execution method so callers can compose commands in a shared transaction.",
        "3. Use a public `IDbContextFactory<ActionsDbContext>` constructor for production command DI; internal `ActionsDbContext` constructors are allowed only for focused tests.",
        "4. In owned mode, create the working DbContext inside the EF execution-strategy delegate before beginning an explicit transaction.",
        "5. In shared mode, use the supplied DbContext and participate in its current transaction when one exists; do not dispose caller-owned contexts.",
        "6. Stage audit rows through `IAuditService.LogAsync(..., dbContext)` when the audit entry must commit or roll back with the aggregate mutation.",
        "7. Use the save (upsert) pattern - determine create vs update by `dto.Id == Guid.Empty`.",
        "8. Use DI-registered `EntityMapper` classes that return `EntityMapperResult<T>` for the mapping step in save commands.",
        "9. Save commands return `CommandResult<EntityMapperResult<T>>` or a feature-specific `CommandResult<T>` - check `Succeeded` before accessing `Value`.",
        "10. Delete commands return `CommandResult` - protection checks return `CommandResult.Fail(...)`.",
        "11. Lifecycle/action commands return `CommandResult` or `CommandResult<T>` - expected errors return `Fail(...)`.",
        "12. Check for empty mapper result on update (entity not found) - return `Fail(404)`.",
        "13. Use `SaveRequest : EntityDTO` inheritance when the write shape matches the read DTO.",
        "14. Call `AddRange`/`UpdateRange` on `EntityMapperResult` lists.",
        "15. Wrap `SaveChangesAsync` in try/catch for expected TOCTOU unique/concurrency conflicts and return `Fail(409)`.",
        "16. Use explicit transactions for multi-table deletes and aggregate lifecycle commands that write multiple rows.",
        "17. Use `ExecuteDeleteAsync` for hard deletes - never load-and-delete with `RemoveRange`.",
        "18. Use soft delete where ADR-CORE-0020 requires historical preservation.",
        "19. Wrap non-transactional post-save side effects in individual try/catch blocks.",
        "20. Use `Guid.CreateVersion7()` for new entity IDs.",
        "",
        "### SHOULD",
        "",
        "1. Validate referential integrity before save.",
        "2. Check system protection before mutation.",
        "",
        "### MUST NOT",
        "",
        "1. Create separate Create/Update commands - use a single Save command.",
        "2. Use static extension method mappers - use DI-registered `EntityMapper` classes.",
        "3. Query data for display inside commands - use the Query pattern.",
        "4. Publish events directly from commands unless a documented feature design requires transactional outbox semantics.",
        "5. Write audit rows directly from commands - use `IAuditService` with the shared DbContext parameter when audit is transactional.",
        "6. Use `SaveResult` with boolean flags - use `CommandResult` variants.",
        "7. Use `OneOf<>` for any command return type - use `CommandResult` variants.",
        "8. Throw exceptions for expected domain outcomes.",
        "9. Use `Guid?` with null to signal create - use `Guid.Empty`.",
        "10. Open a transaction outside EF's execution strategy in owned mode when retries are enabled.",
        ""
      ],
      "section_type": "narrative",
      "sort_order": 11,
      "heading_level": 2,
      "created_at": "2026-07-17T12:58:34.4311944+00:00"
    },
    {
      "id": "01KXR2GGPGEWYV9Q1SANDXNQFG",
      "title": "See Also",
      "content": [
        "- [Queries](queries.md) — Read operations",
        "- [EntityMapper](entity-mapper.md) — DI-registered `EntityMapper` classes returning `EntityMapperResult<T>`",
        "- [Endpoints](endpoints.md) — How endpoints orchestrate commands and handle results",
        "- [Requests](requests.md) — Contract types, `SaveRequest : EntityDTO` pattern, `Guid.Empty` convention",
        "- [Vertical Slice](vertical-slice.md) — Folder structure and file placement"
      ],
      "section_type": "see-also",
      "sort_order": 12,
      "heading_level": 2,
      "created_at": "2026-07-17T12:58:34.5768861+00:00"
    }
  ]
}
