{
  "id": "01KXX8WNRQTR4EFE93BBX2JTQR",
  "module_id": "01KXR4WNPW86216H643PZ6KA36",
  "ref_code": "NG5",
  "text": [
    "Implement automatic rollover, sinking funds, percentage allocation, income-linked rules, weekly or annual plans, variable pay-cycle budgets, or a generic recurring policy engine in v1."
  ],
  "rationale": [
    "These multiply effective-value and revision semantics beyond the explicit fixed monthly-plan root problem and the M complexity budget; discovery may still choose a fixed non-calendar monthly start day."
  ],
  "created_at": "2026-07-19T13:26:16.6007949+00:00"
}
