{
  "id": "01KXX8Z9KE444YTYWK624XR4FD",
  "module_id": "01KXR4WNPW86216H643PZ6KA36",
  "term": "Budget Position",
  "definition": [
    "A deterministic snapshot-bound comparison of one explicit Budget Plan Revision with public LEDGER actuals. Without a revision selector it uses the single Active revision; an explicit Draft, Active, or Superseded revision may be evaluated without changing lifecycle state. The result returns exact planned, actual, remaining or over, Unbudgeted Spend, and Uncategorized Spend values plus revision status and provenance."
  ],
  "source": "prd",
  "created_at": "2026-07-19T13:27:42.4477241+00:00"
}
