{
  "id": "01KXSX0T6ZF6721V2KH6F0B6CE",
  "module_id": "01KXR4WN5YEX7RT6D1GJ30SCJN",
  "ref_code": "DM-LEDGER-IDEMPOTENCY-RECORD",
  "name": "IdempotencyAndLogicalEffectIdentity",
  "description": [
    "Atomic replay outcomes plus domain-level uniqueness for evidence registration and Reconciliation Decision."
  ],
  "schema_def": [
    "idempotency_record: key, operationId, canonicalRequestHash, actor, state committed, stableResult, committedAt; unique key. Same key and request returns the stored logical result; changed operation or request conflicts. evidence logical identity: kind plus privacy-safe digest unique for one real item, with optional content fingerprint conflict guard. Identical logical evidence registered under a different request key returns the existing record and, for atomic transaction capture, the existing actively linked transaction outcome; it never creates another fact. A changed observation or financial fact conflicts. reconciliation logical identity: evidenceId plus active disposition scope and decision predecessor; confirm, reject, revoke, replace, and coverage completion each have stable uniqueness. Domain effect and request outcome commit together; filesystem artifacts reconcile from committed database state after crashes."
  ],
  "created_at": "2026-07-18T06:01:06.0163586+00:00",
  "links": [
    {
      "id": "01KXSXDS6YK3ES0HBD9DHYJXA8",
      "target_type": "requirement",
      "target": "FR-LEDGER-IDEMPOTENT-WRITES",
      "rel": "implements",
      "created_at": "2026-07-18T06:08:10.9755958+00:00"
    }
  ]
}
